pyhlml/__init__.py
pyhlml/hlml_error.py
pyhlml/hlml_lib.py
pyhlml/hlml_types.py
pyhlml/main.py
pyhlml/pyhlml_types_generated.py
habana_pyhlml-1.23.0.695.dist-info/LICENSE
habana_pyhlml-1.23.0.695.dist-info/METADATA
habana_pyhlml-1.23.0.695.dist-info/WHEEL
habana_pyhlml-1.23.0.695.dist-info/top_level.txt
habana_pyhlml-1.23.0.695.dist-info/RECORD
