Metadata-Version: 2.1
Name: habana-pyhlml
Version: 1.23.0.695
Summary: Python3 wrapper for the HLML library.
Home-page: UNKNOWN
Author: HabanaAI
Author-email: "support@habana.ai"
License: MIT
Platform: UNKNOWN
Classifier: Programming Language :: Python :: 3
Classifier: Operating System :: POSIX :: Linux
Requires-Python: >=3.6
License-File: LICENSE
